{
  "nomeCorso": "Internet technology and protocols",
  "docente": [
    {
      "first_name": "Stefano Domenico",
      "second_name": "Salsano "
    }
  ],
  "annoAccademico": "2020-2021",
  "crediti": "6",
  "settore": "ING-INF/03",
  "anno": "2",
  "semestre": "1",
  "propedeuticit\u00e0": "Nessuna",
  "comunicazioni": [],
  "lezioni": [],
  "materiale": [],
  "programma": "<table><tr><td>null</td></tr></table>",
  "testiRiferimento": "<table><tr><td>null</td></tr></table>",
  "ricevimento": "<table><tr><td>null</td></tr></table>",
  "modalit\u00e0Esame": "<table><tr><td>null</td></tr></table>"
}